clscurves/__init__.py
clscurves/binomial_ci.py
clscurves/config.py
clscurves/covariance.py
clscurves/generator.py
clscurves/plotter/__init__.py
clscurves/plotter/cost.py
clscurves/plotter/dist.py
clscurves/plotter/plotter.py
clscurves/plotter/pr.py
clscurves/plotter/prg.py
clscurves/plotter/prob_calibration.py
clscurves/plotter/rf.py
clscurves/plotter/roc.py
clscurves/tests/__init__.py
clscurves/tests/test_config.py
clscurves/tests/test_generator.py
clscurves/utils.py
clscurves-0.4.0.dist-info/LICENSE
clscurves-0.4.0.dist-info/WHEEL
clscurves-0.4.0.dist-info/METADATA
clscurves-0.4.0.dist-info/RECORD
