Metadata-Version: 2.1
Name: clscurves
Version: 0.4.0
Summary: Compute and plot bootstrapped performance curves for classification problems.
Home-page: https://github.com/chrismbryant/classification-curves
Author: Christopher Bryant
Author-email: cbryant@berkeley.edu
Maintainer: Christopher Bryant
Maintainer-email: cbryant@berkeley.edu
Requires-Python: >=3.10.0,<3.13
Classifier: Programming Language :: Python :: 3
Classifier: Programming Language :: Python :: 3.10
Classifier: Programming Language :: Python :: 3.11
Requires-Dist: matplotlib (>=3.8.2,<4.0.0)
Requires-Dist: mpl-scatter-density (>=0.7,<0.8)
Requires-Dist: numpy (>=1.20.3,<2.0.0)
Requires-Dist: pandas (>=1.2.4,<3.0.0)
Requires-Dist: psutil (>=5.9.5,<6.0.0)
Requires-Dist: scipy (>=1.6.3,<2.0.0)
Requires-Dist: tqdm (>=4.65.0,<5.0.0)
Project-URL: Repository, https://github.com/chrismbryant/classification-curves
